ALM/__init__.py
ALM-0.0.1.dist-info/COPYING.txt
ALM-0.0.1.dist-info/LICENSE.txt
ALM-0.0.1.dist-info/METADATA
ALM-0.0.1.dist-info/WHEEL
ALM-0.0.1.dist-info/top_level.txt
ALM-0.0.1.dist-info/RECORD
