Metadata-Version: 2.1
Name: ALM
Version: 0.0.1
Summary: ALM Model in Python
Home-page: https://github.com/ActMartin/PyALM
Author: Martin Zhao
Author-email: martin@pku.edu.cn
License: UNKNOWN
Platform: UNKNOWN
Classifier: Programming Language :: Python :: 3
Classifier: License :: OSI Approved :: MIT License
Classifier: Operating System :: OS Independent
